{
    "template" : "blank-canvas",
    "pagetitle": "Project Details",
    "content" : "<!-- wp:pattern {\"slug\":\"woodzone\/woodzone-gutenverse-header\"} \/-->\n\n<!-- wp:gutenverse\/section {\"width\":{\"Desktop\":\"1170\"},\"gap\":\"no\",\"elementId\":\"guten-IZJ02u\",\"background\":{\"videoPlayOnMobile\":false,\"type\":\"default\",\"image\":{\"Desktop\":{\"id\":843,\"image\":\"https:\/\/designer.gutenverse.com\/woodzone\/wp-content\/uploads\/sites\/89\/2024\/11\/machine-wood.webp\"}},\"position\":{\"Desktop\":\"custom\",\"Mobile\":\"center center\"},\"yposition\":{\"Desktop\":{\"unit\":\"%\",\"point\":\"99\"}},\"xposition\":{\"Desktop\":{\"point\":\"0\",\"unit\":\"px\"}},\"repeat\":{\"Desktop\":\"no-repeat\",\"Mobile\":\"no-repeat\"},\"size\":{\"Desktop\":\"cover\",\"Mobile\":\"cover\"},\"width\":{\"Mobile\":{\"unit\":\"%\",\"point\":\"100\"}}},\"backgroundOverlay\":{\"type\":\"default\",\"color\":{\"r\":18,\"g\":18,\"b\":18,\"a\":1}},\"opacity\":\"0.8\",\"margin\":{\"Desktop\":[],\"Mobile\":[],\"Tablet\":[]},\"padding\":{\"Desktop\":{\"unit\":\"px\",\"dimension\":{\"top\":\"325\",\"right\":\"0\",\"bottom\":\"150\",\"left\":\"0\"}},\"Mobile\":{\"unit\":\"px\",\"dimension\":{\"top\":\"210\",\"right\":\"0\",\"bottom\":\"90\",\"left\":\"0\"}},\"Tablet\":{\"unit\":\"px\",\"dimension\":{\"top\":\"300\",\"right\":\"20\",\"bottom\":\"130\",\"left\":\"20\"}}}} -->\n<div class=\"section-wrapper\" data-id=\"IZJ02u\"><section class=\"wp-block-gutenverse-section guten-element guten-section guten-IZJ02u layout-boxed align-stretch\"><div class=\"guten-background-overlay\"><\/div><div class=\"guten-container guten-column-gap-no\"><!-- wp:gutenverse\/column {\"width\":{\"Desktop\":100,\"Mobile\":null},\"elementId\":\"guten-auggqg\",\"horizontalAlign\":{\"Desktop\":\"center\"}} -->\n<div class=\"wp-block-gutenverse-column guten-element guten-column guten-auggqg\"><div class=\"guten-column-wrapper\" data-id=\"auggqg\"><!-- wp:gutenverse\/heading {\"elementId\":\"guten-zWRbNA\",\"textAlign\":{\"Desktop\":\"center\"},\"color\":{\"type\":\"variable\",\"id\":\"theme-5\"},\"typography\":{\"type\":\"variable\",\"id\":\"nMGsuT\",\"font\":{\"label\":\"Lato\",\"value\":\"Lato\",\"type\":\"google\"},\"size\":{\"Desktop\":{\"point\":\"36\",\"unit\":\"px\"},\"Mobile\":{\"point\":\"24\",\"unit\":\"px\"}},\"weight\":\"600\",\"lineHeight\":{\"Desktop\":{\"unit\":\"em\",\"point\":\"1.2\"}}},\"margin\":{\"Mobile\":{\"unit\":\"px\",\"dimension\":{\"top\":\"0\",\"right\":\"0\",\"bottom\":\"10\",\"left\":\"0\"}}},\"padding\":{\"Mobile\":[]}} -->\n<h2 class=\"wp-block-gutenverse-heading guten-element guten-zWRbNA\">Project Details<\/h2>\n<!-- \/wp:gutenverse\/heading -->\n\n<!-- wp:gutenverse\/icon-list {\"elementId\":\"guten-3JXk16\",\"displayInline\":true,\"spaceBetween\":{\"Mobile\":\"5\",\"Tablet\":\"5\",\"Desktop\":\"5\"},\"alignList\":{\"Desktop\":\"center\"},\"iconColor\":{\"type\":\"variable\",\"id\":\"theme-3\"},\"textColor\":{\"type\":\"variable\",\"id\":\"theme-5\"},\"textTypography\":{\"type\":\"variable\",\"id\":\"k2MSOO\",\"font\":{\"label\":\"Heebo\",\"value\":\"Heebo\",\"type\":\"google\"},\"lineHeight\":{\"Desktop\":{\"unit\":\"em\",\"point\":\"1.5\"}},\"transform\":\"normal\",\"size\":{\"Desktop\":{\"point\":\"16\",\"unit\":\"px\"},\"Mobile\":{\"point\":\"14\",\"unit\":\"px\"}},\"weight\":\"400\"}} -->\n<div class=\"guten-element guten-icon-list guten-3JXk16 inline-icon-list\"><!-- wp:gutenverse\/icon-list-item {\"elementId\":\"guten-Jy5EYL\",\"hideIcon\":true} -->\n<div class=\"guten-element guten-icon-list-item guten-Jy5EYL\"><a id=\"guten-Jy5EYL\"><span class=\"list-text no-icon\">Home<\/span><\/a><\/div>\n<!-- \/wp:gutenverse\/icon-list-item -->\n\n<!-- wp:gutenverse\/icon-list-item {\"elementId\":\"guten-wn4NzX\"} -->\n<div class=\"guten-element guten-icon-list-item guten-wn4NzX\"><a id=\"guten-wn4NzX\"><i class=\"gtn gtn-angle-right-solid\"><\/i><span class=\"list-text \">Projects Details<\/span><\/a><\/div>\n<!-- \/wp:gutenverse\/icon-list-item --><\/div>\n<!-- \/wp:gutenverse\/icon-list --><\/div><\/div>\n<!-- \/wp:gutenverse\/column --><\/div><\/section><\/div>\n<!-- \/wp:gutenverse\/section -->\n\n<!-- wp:gutenverse\/section {\"width\":{\"Desktop\":\"1170\"},\"gap\":\"no\",\"elementId\":\"guten-Mq5WhH\",\"margin\":{\"Desktop\":[],\"Tablet\":[],\"Mobile\":[]},\"padding\":{\"Desktop\":{\"unit\":\"px\",\"dimension\":{\"top\":\"100\",\"right\":\"0\",\"bottom\":\"100\",\"left\":\"0\"}},\"Tablet\":{\"unit\":\"px\",\"dimension\":{\"top\":\"80\",\"right\":\"20\",\"bottom\":\"80\",\"left\":\"20\"}},\"Mobile\":{\"unit\":\"px\",\"dimension\":{\"top\":\"40\",\"right\":\"20\",\"bottom\":\"40\",\"left\":\"20\"}}}} -->\n<div class=\"section-wrapper\" data-id=\"Mq5WhH\"><section class=\"wp-block-gutenverse-section guten-element guten-section guten-Mq5WhH layout-boxed align-stretch\"><div class=\"guten-container guten-column-gap-no\"><!-- wp:gutenverse\/column {\"width\":{\"Desktop\":100},\"elementId\":\"guten-Ov51Vp\"} -->\n<div class=\"wp-block-gutenverse-column guten-element guten-column guten-Ov51Vp\"><div class=\"guten-column-wrapper\" data-id=\"Ov51Vp\"><!-- wp:gutenverse\/image {\"elementId\":\"guten-IkMTb0\",\"imgSrc\":{\"media\":{\"imageId\":247,\"sizes\":{\"thumbnail\":{\"height\":150,\"width\":150,\"url\":\"https:\/\/designer.gutenverse.com\/woodzone\/wp-content\/uploads\/sites\/89\/2024\/11\/female-carpenters.webp\",\"orientation\":\"landscape\"},\"medium\":{\"height\":200,\"width\":300,\"url\":\"https:\/\/designer.gutenverse.com\/woodzone\/wp-content\/uploads\/sites\/89\/2024\/11\/female-carpenters.webp\",\"orientation\":\"landscape\"},\"large\":{\"height\":682,\"width\":1024,\"url\":\"https:\/\/designer.gutenverse.com\/woodzone\/wp-content\/uploads\/sites\/89\/2024\/11\/female-carpenters.webp\",\"orientation\":\"landscape\"},\"full\":{\"url\":\"https:\/\/designer.gutenverse.com\/woodzone\/wp-content\/uploads\/sites\/89\/2024\/11\/female-carpenters.webp\",\"height\":1333,\"width\":2000,\"orientation\":\"landscape\"}}},\"size\":\"full\"},\"altOriginal\":\"\",\"captionOriginal\":\"\"} -->\n<div class=\"wp-block-gutenverse-image guten-element guten-image guten-IkMTb0\"><div class=\"guten-image-wrapper\"><img class=\"gutenverse-image-box-filled\" src=\"https:\/\/designer.gutenverse.com\/woodzone\/wp-content\/uploads\/sites\/89\/2024\/11\/female-carpenters.webp\" height=\"1333\" width=\"2000\"\/><\/div><\/div>\n<!-- \/wp:gutenverse\/image -->\n\n<!-- wp:gutenverse\/section {\"width\":{\"Desktop\":\"1170\"},\"isChild\":true,\"gap\":\"no\",\"elementId\":\"guten-OtvusM\",\"margin\":{\"Desktop\":{\"unit\":\"px\",\"dimension\":{\"top\":\"40\",\"right\":\"0\",\"bottom\":\"0\",\"left\":\"0\"}}},\"padding\":{\"Desktop\":[]}} -->\n<div class=\"section-wrapper\" data-id=\"OtvusM\"><section class=\"wp-block-gutenverse-section guten-element guten-section guten-OtvusM layout-boxed align-stretch\"><div class=\"guten-container guten-column-gap-no\"><!-- wp:gutenverse\/column {\"width\":{\"Desktop\":75.428,\"Tablet\":100,\"Mobile\":null},\"elementId\":\"guten-CWYcvu\",\"margin\":{\"Desktop\":[],\"Mobile\":[]},\"padding\":{\"Desktop\":{\"unit\":\"px\",\"dimension\":{\"top\":\"0\",\"right\":\"0\",\"bottom\":\"0\",\"left\":\"0\"}},\"Mobile\":{\"unit\":\"px\",\"dimension\":{\"top\":\"0\",\"right\":\"0\",\"bottom\":\"0\",\"left\":\"0\"}}}} -->\n<div class=\"wp-block-gutenverse-column guten-element guten-column guten-CWYcvu\"><div class=\"guten-column-wrapper\" data-id=\"CWYcvu\"><!-- wp:gutenverse\/heading {\"elementId\":\"guten-dEFRDo\",\"color\":{\"type\":\"variable\",\"id\":\"theme-0\"},\"typography\":{\"type\":\"variable\",\"id\":\"nMGsuT\",\"font\":{\"label\":\"Lato\",\"value\":\"Lato\",\"type\":\"google\"},\"size\":{\"Desktop\":{\"point\":\"36\",\"unit\":\"px\"},\"Mobile\":{\"point\":\"24\",\"unit\":\"px\"}},\"weight\":\"600\",\"lineHeight\":{\"Desktop\":{\"unit\":\"em\",\"point\":\"1.2\"}}},\"margin\":{\"Desktop\":{\"unit\":\"px\",\"dimension\":{\"top\":\"0\",\"right\":\"0\",\"bottom\":\"0\",\"left\":\"0\"}}},\"padding\":{\"Desktop\":{\"unit\":\"px\",\"dimension\":{\"top\":\"0\",\"right\":\"0\",\"bottom\":\"15\",\"left\":\"0\"}}}} -->\n<h2 class=\"wp-block-gutenverse-heading guten-element guten-dEFRDo\">Wood Custom<\/h2>\n<!-- \/wp:gutenverse\/heading -->\n\n<!-- wp:gutenverse\/text-editor {\"elementId\":\"guten-JA95Fl\",\"textColor\":{\"type\":\"variable\",\"id\":\"theme-2\"},\"typography\":{\"type\":\"variable\",\"id\":\"k2MSOO\",\"font\":{\"label\":\"Heebo\",\"value\":\"Heebo\",\"type\":\"google\"},\"lineHeight\":{\"Desktop\":{\"unit\":\"em\",\"point\":\"1.5\"}},\"transform\":\"normal\",\"size\":{\"Desktop\":{\"point\":\"16\",\"unit\":\"px\"},\"Mobile\":{\"point\":\"14\",\"unit\":\"px\"}},\"weight\":\"400\"}} -->\n<div class=\"guten-element gutenverse-text-editor guten-JA95Fl\"><div class=\"text-content-inner\"><!-- wp:paragraph -->\n<p>Sed ut perspiciatis unde omnis iste natus error sit voluptatem accusantium doloremque laudantium, totam rem aperiam, eaque ipsa quae ab illo inventore veritatis et quasi dicta architecto beatae vitae dicta sunt explicabo. Nemo enim ipsam voluptatem quia totamio voluptas sit aspernatur.<\/p>\n<!-- \/wp:paragraph --><\/div><\/div>\n<!-- \/wp:gutenverse\/text-editor -->\n\n<!-- wp:gutenverse\/text-editor {\"elementId\":\"guten-kLpLvZ\",\"textColor\":{\"type\":\"variable\",\"id\":\"theme-2\"},\"typography\":{\"type\":\"variable\",\"id\":\"k2MSOO\",\"font\":{\"label\":\"Heebo\",\"value\":\"Heebo\",\"type\":\"google\"},\"lineHeight\":{\"Desktop\":{\"unit\":\"em\",\"point\":\"1.5\"}},\"transform\":\"normal\",\"size\":{\"Desktop\":{\"point\":\"16\",\"unit\":\"px\"},\"Mobile\":{\"point\":\"14\",\"unit\":\"px\"}},\"weight\":\"400\"},\"margin\":{\"Desktop\":[]},\"padding\":{\"Desktop\":{\"unit\":\"px\",\"dimension\":{\"top\":\"10\",\"right\":\"0\",\"bottom\":\"30\",\"left\":\"0\"}}}} -->\n<div class=\"guten-element gutenverse-text-editor guten-kLpLvZ\"><div class=\"text-content-inner\"><!-- wp:paragraph -->\n<p>Quis autem vel eum iure reprehenderit qui in ea voluptate velit esse quam nihil molestiae consequatur, vel illum qui delor dolorem eum fugiat quo voluptas nulla pariatur At vero eos et accusamus et iusto odio dignissimos ducimus qui dompin blanditiis praesentium voluptatum.<\/p>\n<!-- \/wp:paragraph --><\/div><\/div>\n<!-- \/wp:gutenverse\/text-editor -->\n\n<!-- wp:gutenverse\/image {\"elementId\":\"guten-3wpUrF\",\"imgSrc\":{\"media\":{\"imageId\":876,\"sizes\":{\"thumbnail\":{\"height\":150,\"width\":150,\"url\":\"https:\/\/designer.gutenverse.com\/woodzone\/wp-content\/uploads\/sites\/89\/2024\/11\/manual-curve.webp\",\"orientation\":\"landscape\"},\"medium\":{\"height\":200,\"width\":300,\"url\":\"https:\/\/designer.gutenverse.com\/woodzone\/wp-content\/uploads\/sites\/89\/2024\/11\/manual-curve.webp\",\"orientation\":\"landscape\"},\"large\":{\"height\":684,\"width\":1024,\"url\":\"https:\/\/designer.gutenverse.com\/woodzone\/wp-content\/uploads\/sites\/89\/2024\/11\/manual-curve.webp\",\"orientation\":\"landscape\"},\"full\":{\"url\":\"https:\/\/designer.gutenverse.com\/woodzone\/wp-content\/uploads\/sites\/89\/2024\/11\/manual-curve.webp\",\"height\":1335,\"width\":2000,\"orientation\":\"landscape\"}}},\"size\":\"full\"},\"altOriginal\":\"\",\"captionOriginal\":\"\",\"width\":{\"Tablet\":{\"unit\":\"%\",\"point\":\"67\"},\"Mobile\":{\"unit\":\"%\",\"point\":\"75\"}},\"imgBorder\":{\"radius\":{\"Desktop\":[]}},\"imgBorderResponsive\":{\"Tablet\":{\"radius\":[]},\"Mobile\":{\"radius\":[]}},\"align\":{\"Mobile\":\"left\"},\"margin\":{\"Tablet\":[],\"Mobile\":[]},\"padding\":{\"Tablet\":{\"unit\":\"px\",\"dimension\":{\"top\":\"\",\"right\":\"\",\"bottom\":\"\",\"left\":\"\"}},\"Mobile\":[]},\"positioningType\":{\"Desktop\":\"custom\",\"Tablet\":\"full\",\"Mobile\":\"full\"},\"positioningWidth\":{\"Desktop\":{\"unit\":\"%\",\"point\":\"50\"}}} -->\n<div class=\"wp-block-gutenverse-image guten-element guten-image guten-3wpUrF\"><div class=\"guten-image-wrapper\"><img class=\"gutenverse-image-box-filled\" src=\"https:\/\/designer.gutenverse.com\/woodzone\/wp-content\/uploads\/sites\/89\/2024\/11\/manual-curve.webp\" height=\"1335\" width=\"2000\"\/><\/div><\/div>\n<!-- \/wp:gutenverse\/image -->\n\n<!-- wp:gutenverse\/icon-list {\"elementId\":\"guten-LzOXRV\",\"spaceBetween\":{\"Desktop\":\"15\"},\"iconColor\":{\"type\":\"variable\",\"id\":\"theme-3\"},\"iconSize\":{\"Desktop\":\"14\"},\"textColor\":{\"type\":\"variable\",\"id\":\"theme-2\"},\"textIndent\":{\"Desktop\":\"10\"},\"textTypography\":{\"type\":\"variable\",\"id\":\"k2MSOO\",\"font\":{\"label\":\"Heebo\",\"value\":\"Heebo\",\"type\":\"google\"},\"lineHeight\":{\"Desktop\":{\"unit\":\"em\",\"point\":\"1.5\"}},\"transform\":\"normal\",\"size\":{\"Desktop\":{\"point\":\"16\",\"unit\":\"px\"},\"Mobile\":{\"point\":\"14\",\"unit\":\"px\"}},\"weight\":\"400\"},\"margin\":{\"Desktop\":[],\"Tablet\":[]},\"padding\":{\"Desktop\":{\"unit\":\"px\",\"dimension\":{\"top\":\"0\",\"right\":\"0\",\"bottom\":\"0\",\"left\":\"40\"}},\"Tablet\":{\"unit\":\"px\",\"dimension\":{\"top\":\"30\",\"right\":\"0\",\"bottom\":\"0\",\"left\":\"0\"}}},\"positioningType\":{\"Desktop\":\"custom\",\"Tablet\":\"full\"},\"positioningWidth\":{\"Desktop\":{\"unit\":\"%\",\"point\":\"50\"}}} -->\n<div class=\"guten-element guten-icon-list guten-LzOXRV\"><!-- wp:gutenverse\/icon-list-item {\"elementId\":\"guten-f56fil\"} -->\n<div class=\"guten-element guten-icon-list-item guten-f56fil\"><a id=\"guten-f56fil\"><i class=\"fas fa-check\"><\/i><span class=\"list-text \">Vivamus starlord finibus, dictum massa eget, suscipit metus nami at tristique elit started.<\/span><\/a><\/div>\n<!-- \/wp:gutenverse\/icon-list-item -->\n\n<!-- wp:gutenverse\/icon-list-item {\"elementId\":\"guten-59r60z\"} -->\n<div class=\"guten-element guten-icon-list-item guten-59r60z\"><a id=\"guten-59r60z\"><i class=\"fas fa-check\"><\/i><span class=\"list-text \">Cras ipsum libero, suscipit vitamin tellus vitae, feugiat ultricies purus praesent gamora.<\/span><\/a><\/div>\n<!-- \/wp:gutenverse\/icon-list-item -->\n\n<!-- wp:gutenverse\/icon-list-item {\"elementId\":\"guten-UWApid\"} -->\n<div class=\"guten-element guten-icon-list-item guten-UWApid\"><a id=\"guten-UWApid\"><i class=\"fas fa-check\"><\/i><span class=\"list-text \">Proin ex sem, ultrices drax the sit amet, facilisis destrogen et odio profession risusest.<\/span><\/a><\/div>\n<!-- \/wp:gutenverse\/icon-list-item -->\n\n<!-- wp:gutenverse\/icon-list-item {\"elementId\":\"guten-Wnmiqv\"} -->\n<div class=\"guten-element guten-icon-list-item guten-Wnmiqv\"><a id=\"guten-Wnmiqv\"><i class=\"fas fa-check\"><\/i><span class=\"list-text \">Cras ipsum libero, suscipit vitamin tellus vitae, feugiat ultricies purus praesent gamora.<\/span><\/a><\/div>\n<!-- \/wp:gutenverse\/icon-list-item -->\n\n<!-- wp:gutenverse\/icon-list-item {\"elementId\":\"guten-Q6YK9f\"} -->\n<div class=\"guten-element guten-icon-list-item guten-Q6YK9f\"><a id=\"guten-Q6YK9f\"><i class=\"fas fa-check\"><\/i><span class=\"list-text \">Cras ipsum libero, suscipit vitamin tellus vitae, feugiat ultricies purus praesent gamora.<\/span><\/a><\/div>\n<!-- \/wp:gutenverse\/icon-list-item --><\/div>\n<!-- \/wp:gutenverse\/icon-list -->\n\n<!-- wp:gutenverse\/text-editor {\"elementId\":\"guten-06Om73\",\"textColor\":{\"type\":\"variable\",\"id\":\"theme-2\"},\"typography\":{\"type\":\"variable\",\"id\":\"k2MSOO\",\"font\":{\"label\":\"Heebo\",\"value\":\"Heebo\",\"type\":\"google\"},\"lineHeight\":{\"Desktop\":{\"unit\":\"em\",\"point\":\"1.5\"}},\"transform\":\"normal\",\"size\":{\"Desktop\":{\"point\":\"16\",\"unit\":\"px\"},\"Mobile\":{\"point\":\"14\",\"unit\":\"px\"}},\"weight\":\"400\"},\"margin\":{\"Desktop\":[]},\"padding\":{\"Desktop\":{\"unit\":\"px\",\"dimension\":{\"top\":\"30\",\"right\":\"0\",\"bottom\":\"0\",\"left\":\"0\"}}}} -->\n<div class=\"guten-element gutenverse-text-editor guten-06Om73\"><div class=\"text-content-inner\"><!-- wp:paragraph -->\n<p>Sed ut perspiciatis unde omnis iste natus error sit voluptatem accusantium doloremque laudantium, totam rem aperiam, eaque ipsa quae ab illo inventore veritatis et quasi dicta architecto beatae vitae dicta sunt explicabo. Nemo enim ipsam voluptatem quia totamio voluptas sit aspernatur.<br><\/p>\n<!-- \/wp:paragraph --><\/div><\/div>\n<!-- \/wp:gutenverse\/text-editor --><\/div><\/div>\n<!-- \/wp:gutenverse\/column -->\n\n<!-- wp:gutenverse\/column {\"width\":{\"Desktop\":24.57,\"Tablet\":100},\"elementId\":\"guten-8Y22rD\",\"margin\":{\"Desktop\":[],\"Tablet\":{\"unit\":\"px\",\"dimension\":{\"top\":\"40\",\"right\":\"0\",\"bottom\":\"0\",\"left\":\"0\"}}},\"padding\":{\"Desktop\":{\"unit\":\"px\",\"dimension\":{\"top\":\"0\",\"right\":\"0\",\"bottom\":\"0\",\"left\":\"20\"}},\"Tablet\":{\"unit\":\"px\",\"dimension\":{\"top\":\"0\",\"right\":\"0\",\"bottom\":\"0\",\"left\":\"0\"}}}} -->\n<div class=\"wp-block-gutenverse-column guten-element guten-column guten-8Y22rD\"><div class=\"guten-column-wrapper\" data-id=\"8Y22rD\"><!-- wp:gutenverse\/icon-box {\"elementId\":\"guten-Y4Oqne\",\"separateButtonLink\":false,\"title\":\"Client\",\"description\":\"Osman Easton\",\"icon\":\"gtn gtn-user-1-light\",\"iconSize\":{\"Desktop\":\"25\"},\"iconPosition\":\"left\",\"align\":{\"Desktop\":\"flex-start\"},\"containerPadding\":{\"Desktop\":{\"unit\":\"px\",\"dimension\":{\"top\":\"0\",\"right\":\"0\",\"bottom\":\"0\",\"left\":\"0\"}}},\"containerBorder\":{\"radius\":{\"Desktop\":[]},\"all\":{\"type\":\"none\"}},\"iconPadding\":{\"Desktop\":[]},\"iconMargin\":{\"Desktop\":[]},\"iconColor\":{\"type\":\"variable\",\"id\":\"theme-3\"},\"iconBorder\":{\"radius\":{\"Desktop\":[]}},\"titlePadding\":{\"Desktop\":[]},\"titleMargin\":{\"Desktop\":[]},\"titleColor\":{\"type\":\"variable\",\"id\":\"theme-0\"},\"titleTypography\":{\"type\":\"variable\",\"id\":\"XcIu3n\",\"font\":{\"label\":\"Lato\",\"value\":\"Lato\",\"type\":\"google\"},\"size\":{\"Desktop\":{\"point\":\"18\",\"unit\":\"px\"}},\"weight\":\"600\",\"lineHeight\":{\"Desktop\":{\"unit\":\"em\",\"point\":\"0.1\"}}},\"descMargin\":{\"Desktop\":[]},\"descColor\":{\"type\":\"variable\",\"id\":\"theme-2\"},\"descTypography\":{\"type\":\"variable\",\"id\":\"k2MSOO\",\"font\":{\"label\":\"Heebo\",\"value\":\"Heebo\",\"type\":\"google\"},\"lineHeight\":{\"Desktop\":{\"unit\":\"em\",\"point\":\"1.5\"}},\"transform\":\"normal\",\"size\":{\"Desktop\":{\"point\":\"16\",\"unit\":\"px\"},\"Mobile\":{\"point\":\"14\",\"unit\":\"px\"}},\"weight\":\"400\"},\"margin\":{\"Desktop\":[]},\"padding\":{\"Desktop\":{\"unit\":\"px\",\"dimension\":{\"top\":\"0\",\"right\":\"0\",\"bottom\":\"20\",\"left\":\"0\"}}},\"positioningType\":{\"Tablet\":\"custom\"},\"positioningWidth\":{\"Tablet\":{\"unit\":\"%\",\"point\":\"50\"}},\"parentSelector\":\".guten-Y4Oqne:hover .guten-icon-box-wrapper\"} -->\n<div class=\"guten-element guten-Y4Oqne guten-icon-box icon-position-left\"><div class=\"guten-icon-box-wrapper hover-from-left\"><div class=\"icon-box icon-box-header\"><div class=\"icon style-color\"><i class=\"gtn gtn-user-1-light\"><\/i><\/div><\/div><div class=\"icon-box icon-box-body\"><h2 class=\"title\">Client<\/h2><p class=\"icon-box-description\">Osman Easton<\/p><\/div><\/div><\/div>\n<!-- \/wp:gutenverse\/icon-box -->\n\n<!-- wp:gutenverse\/icon-box {\"elementId\":\"guten-bVK772\",\"separateButtonLink\":false,\"title\":\"Date\",\"description\":\"11 Nov 2024\",\"icon\":\"gtn gtn-calendar-light\",\"iconSize\":{\"Desktop\":\"25\"},\"iconPosition\":\"left\",\"align\":{\"Desktop\":\"flex-start\"},\"containerPadding\":{\"Desktop\":{\"unit\":\"px\",\"dimension\":{\"top\":\"0\",\"right\":\"0\",\"bottom\":\"0\",\"left\":\"0\"}}},\"containerBorder\":{\"radius\":{\"Desktop\":[]},\"all\":{\"type\":\"none\"}},\"iconPadding\":{\"Desktop\":[]},\"iconMargin\":{\"Desktop\":[]},\"iconColor\":{\"type\":\"variable\",\"id\":\"theme-3\"},\"iconBorder\":{\"radius\":{\"Desktop\":[]}},\"titlePadding\":{\"Desktop\":[]},\"titleMargin\":{\"Desktop\":[]},\"titleColor\":{\"type\":\"variable\",\"id\":\"theme-0\"},\"titleTypography\":{\"type\":\"variable\",\"id\":\"XcIu3n\",\"font\":{\"label\":\"Lato\",\"value\":\"Lato\",\"type\":\"google\"},\"size\":{\"Desktop\":{\"point\":\"18\",\"unit\":\"px\"}},\"weight\":\"600\",\"lineHeight\":{\"Desktop\":{\"unit\":\"em\",\"point\":\"0.1\"}}},\"descMargin\":{\"Desktop\":[]},\"descColor\":{\"type\":\"variable\",\"id\":\"theme-2\"},\"descTypography\":{\"type\":\"variable\",\"id\":\"k2MSOO\",\"font\":{\"label\":\"Heebo\",\"value\":\"Heebo\",\"type\":\"google\"},\"lineHeight\":{\"Desktop\":{\"unit\":\"em\",\"point\":\"1.5\"}},\"transform\":\"normal\",\"size\":{\"Desktop\":{\"point\":\"16\",\"unit\":\"px\"},\"Mobile\":{\"point\":\"14\",\"unit\":\"px\"}},\"weight\":\"400\"},\"margin\":{\"Desktop\":[]},\"padding\":{\"Desktop\":{\"unit\":\"px\",\"dimension\":{\"top\":\"0\",\"right\":\"0\",\"bottom\":\"20\",\"left\":\"0\"}}},\"positioningType\":{\"Tablet\":\"custom\"},\"positioningWidth\":{\"Tablet\":{\"unit\":\"%\",\"point\":\"50\"}},\"parentSelector\":\".guten-bVK772:hover .guten-icon-box-wrapper\"} -->\n<div class=\"guten-element guten-bVK772 guten-icon-box icon-position-left\"><div class=\"guten-icon-box-wrapper hover-from-left\"><div class=\"icon-box icon-box-header\"><div class=\"icon style-color\"><i class=\"gtn gtn-calendar-light\"><\/i><\/div><\/div><div class=\"icon-box icon-box-body\"><h2 class=\"title\">Date<\/h2><p class=\"icon-box-description\">11 Nov 2024<\/p><\/div><\/div><\/div>\n<!-- \/wp:gutenverse\/icon-box -->\n\n<!-- wp:gutenverse\/icon-box {\"elementId\":\"guten-2SSmws\",\"separateButtonLink\":false,\"title\":\"Category\",\"description\":\"Custom\",\"icon\":\"gtn gtn-file-1-light\",\"iconSize\":{\"Desktop\":\"25\"},\"iconPosition\":\"left\",\"align\":{\"Desktop\":\"flex-start\"},\"containerPadding\":{\"Desktop\":{\"unit\":\"px\",\"dimension\":{\"top\":\"0\",\"right\":\"0\",\"bottom\":\"0\",\"left\":\"0\"}}},\"containerBorder\":{\"radius\":{\"Desktop\":[]},\"all\":{\"type\":\"none\"}},\"iconPadding\":{\"Desktop\":[]},\"iconMargin\":{\"Desktop\":[]},\"iconColor\":{\"type\":\"variable\",\"id\":\"theme-3\"},\"iconBorder\":{\"radius\":{\"Desktop\":[]}},\"titlePadding\":{\"Desktop\":[]},\"titleMargin\":{\"Desktop\":[]},\"titleColor\":{\"type\":\"variable\",\"id\":\"theme-0\"},\"titleTypography\":{\"type\":\"variable\",\"id\":\"XcIu3n\",\"font\":{\"label\":\"Lato\",\"value\":\"Lato\",\"type\":\"google\"},\"size\":{\"Desktop\":{\"point\":\"18\",\"unit\":\"px\"}},\"weight\":\"600\",\"lineHeight\":{\"Desktop\":{\"unit\":\"em\",\"point\":\"0.1\"}}},\"descMargin\":{\"Desktop\":[]},\"descColor\":{\"type\":\"variable\",\"id\":\"theme-2\"},\"descTypography\":{\"type\":\"variable\",\"id\":\"k2MSOO\",\"font\":{\"label\":\"Heebo\",\"value\":\"Heebo\",\"type\":\"google\"},\"lineHeight\":{\"Desktop\":{\"unit\":\"em\",\"point\":\"1.5\"}},\"transform\":\"normal\",\"size\":{\"Desktop\":{\"point\":\"16\",\"unit\":\"px\"},\"Mobile\":{\"point\":\"14\",\"unit\":\"px\"}},\"weight\":\"400\"},\"margin\":{\"Desktop\":[],\"Tablet\":[]},\"padding\":{\"Desktop\":{\"unit\":\"px\",\"dimension\":{\"top\":\"0\",\"right\":\"0\",\"bottom\":\"20\",\"left\":\"0\"}},\"Tablet\":{\"unit\":\"px\",\"dimension\":{\"top\":\"0\",\"right\":\"0\",\"bottom\":\"40\",\"left\":\"0\"}},\"Mobile\":[]},\"positioningType\":{\"Tablet\":\"custom\"},\"positioningWidth\":{\"Tablet\":{\"unit\":\"%\",\"point\":\"50\"}},\"parentSelector\":\".guten-2SSmws:hover .guten-icon-box-wrapper\"} -->\n<div class=\"guten-element guten-2SSmws guten-icon-box icon-position-left\"><div class=\"guten-icon-box-wrapper hover-from-left\"><div class=\"icon-box icon-box-header\"><div class=\"icon style-color\"><i class=\"gtn gtn-file-1-light\"><\/i><\/div><\/div><div class=\"icon-box icon-box-body\"><h2 class=\"title\">Category<\/h2><p class=\"icon-box-description\">Custom<\/p><\/div><\/div><\/div>\n<!-- \/wp:gutenverse\/icon-box -->\n\n<!-- wp:gutenverse\/icon-box {\"elementId\":\"guten-16rhHh\",\"separateButtonLink\":false,\"title\":\"Location\",\"description\":\"Denpasar, Bali\",\"icon\":\"gtn gtn-map-marker1-light\",\"iconSize\":{\"Desktop\":\"25\"},\"iconPosition\":\"left\",\"align\":{\"Desktop\":\"flex-start\"},\"containerPadding\":{\"Desktop\":{\"unit\":\"px\",\"dimension\":{\"top\":\"0\",\"right\":\"0\",\"bottom\":\"0\",\"left\":\"0\"}}},\"containerBorder\":{\"radius\":{\"Desktop\":[]},\"all\":{\"type\":\"none\"}},\"iconPadding\":{\"Desktop\":[]},\"iconMargin\":{\"Desktop\":[]},\"iconColor\":{\"type\":\"variable\",\"id\":\"theme-3\"},\"iconBorder\":{\"radius\":{\"Desktop\":[]}},\"titlePadding\":{\"Desktop\":[]},\"titleMargin\":{\"Desktop\":[]},\"titleColor\":{\"type\":\"variable\",\"id\":\"theme-0\"},\"titleTypography\":{\"type\":\"variable\",\"id\":\"XcIu3n\",\"font\":{\"label\":\"Lato\",\"value\":\"Lato\",\"type\":\"google\"},\"size\":{\"Desktop\":{\"point\":\"18\",\"unit\":\"px\"}},\"weight\":\"600\",\"lineHeight\":{\"Desktop\":{\"unit\":\"em\",\"point\":\"0.1\"}}},\"descMargin\":{\"Desktop\":[]},\"descColor\":{\"type\":\"variable\",\"id\":\"theme-2\"},\"descTypography\":{\"type\":\"variable\",\"id\":\"k2MSOO\",\"font\":{\"label\":\"Heebo\",\"value\":\"Heebo\",\"type\":\"google\"},\"lineHeight\":{\"Desktop\":{\"unit\":\"em\",\"point\":\"1.5\"}},\"transform\":\"normal\",\"size\":{\"Desktop\":{\"point\":\"16\",\"unit\":\"px\"},\"Mobile\":{\"point\":\"14\",\"unit\":\"px\"}},\"weight\":\"400\"},\"margin\":{\"Desktop\":[],\"Tablet\":[]},\"padding\":{\"Desktop\":{\"unit\":\"px\",\"dimension\":{\"top\":\"0\",\"right\":\"0\",\"bottom\":\"20\",\"left\":\"0\"}},\"Tablet\":{\"unit\":\"px\",\"dimension\":{\"top\":\"0\",\"right\":\"0\",\"bottom\":\"40\",\"left\":\"0\"}}},\"positioningType\":{\"Tablet\":\"custom\"},\"positioningWidth\":{\"Tablet\":{\"unit\":\"%\",\"point\":\"50\"}},\"parentSelector\":\".guten-16rhHh:hover .guten-icon-box-wrapper\"} -->\n<div class=\"guten-element guten-16rhHh guten-icon-box icon-position-left\"><div class=\"guten-icon-box-wrapper hover-from-left\"><div class=\"icon-box icon-box-header\"><div class=\"icon style-color\"><i class=\"gtn gtn-map-marker1-light\"><\/i><\/div><\/div><div class=\"icon-box icon-box-body\"><h2 class=\"title\">Location<\/h2><p class=\"icon-box-description\">Denpasar, Bali<\/p><\/div><\/div><\/div>\n<!-- \/wp:gutenverse\/icon-box -->\n\n<!-- wp:gutenverse\/text-editor {\"elementId\":\"guten-HmZLPy\",\"textColor\":{\"type\":\"variable\",\"id\":\"theme-2\"},\"typography\":{\"type\":\"variable\",\"id\":\"k2MSOO\",\"font\":{\"label\":\"Heebo\",\"value\":\"Heebo\",\"type\":\"google\"},\"lineHeight\":{\"Desktop\":{\"unit\":\"em\",\"point\":\"1.5\"}},\"transform\":\"normal\",\"size\":{\"Desktop\":{\"point\":\"16\",\"unit\":\"px\"},\"Mobile\":{\"point\":\"14\",\"unit\":\"px\"}},\"weight\":\"400\"},\"margin\":{\"Tablet\":{\"unit\":\"px\",\"dimension\":{\"top\":\"\",\"right\":\"\",\"bottom\":\"\",\"left\":\"\"}}},\"padding\":{\"Tablet\":{\"unit\":\"px\",\"dimension\":{\"top\":\"10\",\"right\":\"20\",\"bottom\":\"0\",\"left\":\"0\"}}},\"positioningType\":{\"Tablet\":\"inline\"}} -->\n<div class=\"guten-element gutenverse-text-editor guten-HmZLPy\"><div class=\"text-content-inner\"><!-- wp:paragraph -->\n<p>Share This :<\/p>\n<!-- \/wp:paragraph --><\/div><\/div>\n<!-- \/wp:gutenverse\/text-editor -->\n\n<!-- wp:gutenverse\/social-share {\"elementId\":\"guten-fAO6jN\",\"iconPading\":{\"Desktop\":{\"unit\":\"px\",\"dimension\":{\"top\":\"12\",\"right\":\"12\",\"bottom\":\"12\",\"left\":\"12\"}}},\"textPading\":{\"Desktop\":[]},\"iconColor\":{\"type\":\"variable\",\"id\":\"theme-5\"},\"iconBackgroundColor\":{\"type\":\"variable\",\"id\":\"theme-3\"},\"borderType\":{\"radius\":{\"Desktop\":{\"unit\":\"px\",\"dimension\":{\"top\":\"50\",\"right\":\"50\",\"bottom\":\"50\",\"left\":\"50\"}}}},\"iconColorHover\":{\"type\":\"variable\",\"id\":\"theme-5\"},\"iconBackgroundColorHover\":{\"type\":\"variable\",\"id\":\"theme-1\"},\"borderTypeHover\":{\"radius\":{\"Desktop\":[]}},\"iconSize\":{\"Desktop\":{\"point\":\"16\",\"unit\":\"px\"}},\"alignment\":{\"Desktop\":\"flex-start\"},\"gap\":{\"Desktop\":\"20\"},\"border\":{\"radius\":{\"Desktop\":{\"unit\":\"px\",\"dimension\":{\"top\":\"50\",\"right\":\"50\",\"bottom\":\"50\",\"left\":\"50\"}}}},\"margin\":{\"Desktop\":[],\"Tablet\":[]},\"padding\":{\"Desktop\":{\"unit\":\"px\",\"dimension\":{\"top\":\"20\",\"right\":\"0\",\"bottom\":\"0\",\"left\":\"0\"}},\"Tablet\":{\"unit\":\"px\",\"dimension\":{\"top\":\"0\",\"right\":\"0\",\"bottom\":\"0\",\"left\":\"0\"}}},\"positioningType\":{\"Tablet\":\"inline\"}} -->\n<div class=\"guten-element guten-social-share guten-fAO6jN horizontal\"><!-- wp:gutenverse\/social-share-facebook {\"elementId\":\"guten-aghDFh\",\"showText\":false} \/-->\n\n<!-- wp:gutenverse\/social-share-twitter {\"elementId\":\"guten-LCVACs\",\"selectedIcon\":\"x-twitter\",\"showText\":false,\"iconColor\":{\"r\":255,\"g\":255,\"b\":255,\"a\":1},\"iconBackgroundColor\":{\"type\":\"variable\",\"id\":\"theme-3\"},\"border\":{\"radius\":{\"Desktop\":[]}},\"iconColorHover\":{\"r\":255,\"g\":255,\"b\":255,\"a\":1},\"iconBackgroundColorHover\":{\"type\":\"variable\",\"id\":\"theme-1\"},\"borderHover\":{\"radius\":{\"Desktop\":[]}}} \/-->\n\n<!-- wp:gutenverse\/social-share-whatsapp {\"elementId\":\"guten-dEBPj3\",\"showText\":false} \/--><\/div>\n<!-- \/wp:gutenverse\/social-share --><\/div><\/div>\n<!-- \/wp:gutenverse\/column --><\/div><\/section><\/div>\n<!-- \/wp:gutenverse\/section --><\/div><\/div>\n<!-- \/wp:gutenverse\/column --><\/div><\/section><\/div>\n<!-- \/wp:gutenverse\/section -->\n\n<!-- wp:pattern {\"slug\":\"woodzone\/woodzone-about-gutenverse-cta-alt\"} \/-->\n\n<!-- wp:pattern {\"slug\":\"woodzone\/woodzone-gutenverse-footer\"} \/-->",
    "preview_url" : "https://fse.jegtheme.com/woodzone/project-details/",
    "image_url" : "assets/img/project-details.webp",
    "is_homepage" : false,
    "core-patterns" : [],
    "pro-patterns" : [],
    "gutenverse-patterns" : ["woodzone-gutenverse-header", "woodzone-about-gutenverse-cta-alt", "woodzone-gutenverse-footer"],
    "image_arr" : "[{'name':'machine-wood.webp','image_url':'https:\/\/designer.gutenverse.com\/woodzone\/wp-content\/uploads\/sites\/89\/2024\/11\/machine-wood.webp','type':'page','id':12},{'name':'female-carpenters.webp','image_url':'https:\/\/designer.gutenverse.com\/woodzone\/wp-content\/uploads\/sites\/89\/2024\/11\/female-carpenters.webp','type':'page','id':12},{'name':'manual-curve.webp','image_url':'https:\/\/designer.gutenverse.com\/woodzone\/wp-content\/uploads\/sites\/89\/2024\/11\/manual-curve.webp','type':'page','id':12}]"
}